tapcli-0.2.6.data/scripts/tap
tapflow/__init__.py
tapflow/cli/__init__.py
tapflow/cli/cli.py
tapflow/lib/__init__.py
tapflow/lib/cache.py
tapflow/lib/check.py
tapflow/lib/graph.py
tapflow/lib/help_decorator.py
tapflow/lib/login.py
tapflow/lib/op_object.py
tapflow/lib/request.py
tapflow/lib/advanced/__init__.py
tapflow/lib/advanced/cdc_log_cache.py
tapflow/lib/advanced/heartbeat_task.py
tapflow/lib/advanced/live_cache.py
tapflow/lib/connections/__init__.py
tapflow/lib/connections/connection.py
tapflow/lib/connections/connection_list.py
tapflow/lib/data_pipeline/__init__.py
tapflow/lib/data_pipeline/base_node.py
tapflow/lib/data_pipeline/base_obj.py
tapflow/lib/data_pipeline/dag.py
tapflow/lib/data_pipeline/data_source.py
tapflow/lib/data_pipeline/job.py
tapflow/lib/data_pipeline/pipeline.py
tapflow/lib/data_pipeline/nodes/__init__.py
tapflow/lib/data_pipeline/nodes/column_filter.py
tapflow/lib/data_pipeline/nodes/field_add_del.py
tapflow/lib/data_pipeline/nodes/field_calculate.py
tapflow/lib/data_pipeline/nodes/field_rename.py
tapflow/lib/data_pipeline/nodes/filter.py
tapflow/lib/data_pipeline/nodes/js.py
tapflow/lib/data_pipeline/nodes/merge.py
tapflow/lib/data_pipeline/nodes/py.py
tapflow/lib/data_pipeline/nodes/python.py
tapflow/lib/data_pipeline/nodes/rename.py
tapflow/lib/data_pipeline/nodes/rename_table.py
tapflow/lib/data_pipeline/nodes/row_filter.py
tapflow/lib/data_pipeline/nodes/sink.py
tapflow/lib/data_pipeline/nodes/source.py
tapflow/lib/data_pipeline/nodes/time_add.py
tapflow/lib/data_pipeline/nodes/time_adjust.py
tapflow/lib/data_pipeline/nodes/type_filter.py
tapflow/lib/data_pipeline/nodes/type_modification.py
tapflow/lib/data_pipeline/nodes/union.py
tapflow/lib/data_pipeline/nodes/unwind.py
tapflow/lib/data_pipeline/nodes/value_map.py
tapflow/lib/data_pipeline/validation/__init__.py
tapflow/lib/data_pipeline/validation/any_table_verify.py
tapflow/lib/data_pipeline/validation/data_verify.py
tapflow/lib/data_services/__init__.py
tapcli-0.2.6.dist-info/METADATA
tapcli-0.2.6.dist-info/WHEEL
tapcli-0.2.6.dist-info/top_level.txt
tapcli-0.2.6.dist-info/RECORD
