Metadata-Version: 2.1
Name: tapcli
Version: 0.2.6
Classifier: Programming Language :: Python :: 3
Classifier: License :: OSI Approved :: MIT License
Classifier: Operating System :: OS Independent
Requires-Python: >=3.6
Requires-Dist: requests
Requires-Dist: pyyaml
Requires-Dist: websockets
Requires-Dist: bson
Requires-Dist: ipython
